shopify_api_client/__init__.py
shopify_api_client-0.2.2.dist-info/METADATA
shopify_api_client-0.2.2.dist-info/WHEEL
shopify_api_client-0.2.2.dist-info/RECORD
