Metadata-Version: 2.1
Name: shopify_api_client
Version: 0.2.2
Summary: 
Author: Brayden Brekke
Author-email: Braydenbrekke@live.com
Requires-Python: >=3.9,<4.0
Classifier: Programming Language :: Python :: 3
Classifier: Programming Language :: Python :: 3.9
Classifier: Programming Language :: Python :: 3.10
Classifier: Programming Language :: Python :: 3.11
Classifier: Programming Language :: Python :: 3.12
Requires-Dist: datetime (>=5.5,<6.0)
Requires-Dist: pytz (>=2024.1,<2025.0)
Requires-Dist: requests (>=2.32.3,<3.0.0)
